ispcr/FastaSequence.py
ispcr/__init__.py
ispcr/py.typed
ispcr/utils.py
ispcr-0.9.1.dist-info/METADATA
ispcr-0.9.1.dist-info/LICENSE
ispcr-0.9.1.dist-info/WHEEL
ispcr-0.9.1.dist-info/RECORD
